{"stats":{"minecraft:broken":{"iceandfire:armor_gray_boots":1,"iceandfire:armor_gray_chestplate":1,"iceandfire:armor_gray_leggings":1},"minecraft:mined":{"minecraft:dark_oak_planks":3,"minecraft:white_bed":1,"botania:red_mystical_flower":13,"minecraft:jungle_leaves":1,"minecraft:granite":19,"minecraft:acacia_log":2,"minecraft:tall_seagrass":2,"botania:purple_mystical_flower":14,"extcaves:mushroom_lumishroom":2,"minecraft:fletching_table":1,"powah:uraninite_ore_poor":1,"forbidden_arcanus:dark_beacon":2,"botania:green_mystical_flower":10,"mekanism:basic_infusing_factory":1,"mekanism:osmium_ore":4,"minecraft:brown_mushroom":1,"mekanism:enrichment_chamber":3,"pamhc2trees:pamsoursop":1,"upgrade_aquatic:blue_pickerelweed":1,"byg:soapstone":1,"quark:spruce_vertical_slab":3,"minecraft:wither_rose":1,"upgrade_aquatic:tall_blue_pickerelweed":1,"minecraft:grass":31,"minecraft:mossy_cobblestone":5,"pamhc2trees:pamlemon":1,"minecraft:jungle_planks":1,"betterdefaultbiomes:dune_grass":1,"pamhc2trees:pamcherry":1,"minecraft:andesite":61,"elementalcraft:burnt_glass_pane":14,"astralsorcery:glow_flower":14,"elementalcraft:whiterock_slab":1,"minecraft:vine":1,"byg:rocky_stone":10,"simplefarming:blueberry_bush":8,"mekanism:crusher":1,"botania:lime_mystical_flower":10,"minecraft:potted_lily_of_the_valley":1,"minecraft:brown_carpet":2,"thermal:bell_pepper":1,"elementalcraft:whiterock":7,"minecraft:tall_grass":1,"minecraft:diorite":193,"craftingstation:crafting_station":1,"minecraft:spruce_log":130,"druidcraft:lavender":4,"upgrade_aquatic:flowering_rush":1,"botania:white_mystical_flower":12,"minecraft:gravel":6,"byg:palo_verde_log":13,"pamhc2trees:pampeach":2,"botania:gray_mystical_flower":2,"minecraft:stone_bricks":5,"minecraft:fern":3,"simplefarming:raspberry_bush":9,"minecraft:spruce_planks":2,"pamhc2trees:pambanana":4,"minecraft:brewing_stand":1,"minecraft:grass_block":3188,"mekanism:osmium_compressor":2,"forbidden_arcanus:cherrywood_log":71,"simplefarming:blackberry_bush":2,"simplefarming:apple_leaves":5,"minecraft:iron_ore":18,"upgrade_aquatic:purple_pickerelweed":5,"cyclic:flower_cyan":9,"minecraft:iron_bars":1,"minecraft:potted_cornflower":1,"simplefarming:fruit_log":4,"minecraft:spruce_slab":52,"minecraft:green_bed":2,"minecraft:clay":16,"minecraft:jungle_stairs":1,"minecraft:chest":10,"thermal:peanut":1,"iceandfire:fire_lily":1,"minecraft:cobblestone":1,"botania:blue_mystical_flower":10,"pamhc2crops:shadedgarden":3,"minecraft:oak_planks":2,"minecraft:seagrass":1,"upgrade_aquatic:tall_purple_pickerelweed":18,"pamhc2trees:pamguava":1,"pamhc2trees:pamavocado":1,"minecraft:diorite_wall":1,"minecraft:sand":518,"minecraft:dirt":300,"byg:orange_daisy":2,"pamhc2trees:pamplum":1,"cyclic:clock":1,"minecraft:potted_red_tulip":1,"extcaves:treasure_pot_long":1,"pamhc2trees:pamorange":1,"silentgear:wild_flax_plant":3,"minecraft:oak_door":7,"upgrade_aquatic:embedded_ammonite":1,"gravestone:gravestone":2,"minecraft:spruce_leaves":1,"minecraft:sandstone":8,"minecraft:large_fern":1,"minecraft:hay_block":18,"pamhc2trees:pampeppercorn":1,"immersiveengineering:treated_wood_horizontal":13,"minecraft:black_concrete":8,"minecraft:gold_block":18,"minecraft:bookshelf":12,"forbidden_arcanus:cherrywood_leaves":16,"minecraft:stone":11,"simplefarming:strawberry_bush":6,"minecraft:podzol":2,"druidcraft:elder_leaf_layer":2,"minecraft:acacia_leaves":1,"simplefarming:quinoa":1,"pamhc2crops:windygarden":161,"minecraft:oak_fence":1,"minecraft:crafting_table":2,"mekanism:metallurgic_infuser":1,"botania:white_double_flower":1,"minecraft:spruce_stairs":16,"botania:pink_mystical_flower":8,"mekanism:qio_drive_array":1,"forbidden_arcanus:edelwood_log":4,"minecraft:ice":2,"byg:short_grass":3,"pamhc2crops:soggygarden":1,"minecraft:coal_ore":2,"botania:yellow_mystical_flower":1,"appliedenergistics2:sky_stone_block":259,"simplefarming:chicory":4,"minecraft:cracked_stone_bricks":3,"upgrade_aquatic:driftwood_log":17,"minecraft:mossy_stone_bricks":5},"minecraft:killed_by":{"minecraft:zombie":3,"iceandfire:ghost":1,"iceandfire:sea_serpent":1,"productivebees:yellow_black_carpenter_bee":1,"minecraft:enderman":2,"minecraft:iron_golem":11},"minecraft:killed":{"minecraft:iron_golem":1,"minecraft:zombie":3,"eidolon:wraith":3,"craftandhunt:iron_summon":1,"aquaculture:perch":1,"minecraft:creeper":1,"eidolon:zombie_brute":2,"minecraft:drowned":1,"minecraft:squid":3},"minecraft:custom":{"minecraft:interact_with_crafting_table":3,"minecraft:open_barrel":2,"minecraft:bell_ring":2,"minecraft:leave_game":4,"minecraft:time_since_death":354398,"minecraft:deaths":19,"minecraft:jump":5457,"minecraft:interact_with_furnace":4,"minecraft:traded_with_villager":1,"minecraft:interact_with_cartography_table":1,"minecraft:sleep_in_bed":2,"minecraft:waystone_activated":21,"minecraft:damage_dealt":5844,"minecraft:interact_with_smoker":1,"minecraft:interact_with_anvil":2,"minecraft:sneak_time":7073,"minecraft:time_since_rest":47,"minecraft:use_wand":53,"minecraft:swim_one_cm":57429,"minecraft:fly_one_cm":1320373,"minecraft:open_chest":112,"minecraft:fall_one_cm":194098,"minecraft:sprint_one_cm":490856,"minecraft:drop":112,"minecraft:talked_to_villager":12,"minecraft:interact_with_brewingstand":1,"minecraft:walk_on_water_one_cm":50478,"minecraft:play_one_minute":493178,"minecraft:crouch_one_cm":18121,"minecraft:mob_kills":16,"minecraft:climb_one_cm":6256,"minecraft:walk_one_cm":798256,"minecraft:walk_under_water_one_cm":22695,"minecraft:boat_one_cm":1140381,"minecraft:pot_flower":3,"minecraft:damage_taken":14161,"minecraft:damage_absorbed":47,"minecraft:trigger_trapped_chest":2},"minecraft:picked_up":{"pamhc2crops:wintersquashitem":17,"torchmaster:feral_flare_lantern":64,"forbidden_arcanus:soul_extractor":1,"simplefarming:sorghum_bread":1,"pamhc2crops:cucumberitem":27,"minecraft:flower_pot":3,"xreliquary:pedestals/passive/gray_passive_pedestal":1,"mekanism:nutritional_liquifier":1,"minecraft:lead":5,"minecraft:wither_rose":1,"byg:palo_verde_sapling":8,"rats:rat_and_crossbones_banner_pattern":1,"refinedstorage:controller":1,"minecraft:brewing_stand":1,"simplefarming:cumin_seeds":1,"adhooks:pudge_launcher":1,"create:piston_extension_pole":1,"enigmaticlegacy:thicc_scroll":1,"druidcraft:lavender":5,"mysticalagriculture:inferium_essence":9,"mekanism:basic_universal_cable":25,"simplefarming:fruit_log":4,"minecraft:spruce_planks":2,"thermal:bronze_coin":1,"mcwtrpdoors:print_four_panel":2,"simplefarming:blackberry_bush":2,"upgrade_aquatic:mulberry":1,"economyinc:item_creditcard":5,"silentgems:soul_gem":3,"enigmaticlegacy:super_magnet_ring":1,"powah:energy_cell_blazing":1,"iceandfire:dragonarmor_diamond_neck":1,"minecraft:green_bed":2,"minecraft:acacia_log":2,"simplefarming:raspberries":37,"cyclic:clock":1,"refinedstorage:disk_drive":1,"pamhc2crops:barleyseeditem":1,"minecraft:brown_carpet":2,"botania:white_mystical_flower":12,"botania:ancient_will_guthan":1,"botania:manasteel_ingot":1,"pamhc2crops:peanutitem":26,"minecraft:red_tulip":1,"rftoolsutility:crafter1":1,"forbidden_arcanus:cherry_peach":4,"rats:rat_nugget":1,"minecraft:iron_bars":1,"upgradednetherite:phantom_upgraded_netherite_sword":1,"iceandfire:dragonscale_sapphire":2,"pamhc2trees:bananaitem":4,"rats:rat_upgrade_dragon":1,"ars_nouveau:sylph_charm":1,"minecraft:flint":2,"upgradednetherite:ender_upgraded_netherite_axe":1,"upgrade_aquatic:flowering_rush":4,"pamhc2trees:cherryitem":1,"dankstorage:dock":1,"craftandhunt:bear_polar_helmet":1,"cyclic:flower_cyan":11,"mekanism:alloy_reinforced":2,"simplefarming:cucumber_seeds":2,"simplefarming:sunflower_seeds":2,"mekanism:basic_infusing_factory":2,"simplefarming:blueberry_bush":7,"simplefarming:tomato_seeds":1,"crossroads:molten_copper_bucket":1,"minecraft:glowstone_dust":67,"simplefarming:peanut_seeds":1,"mekanism:metallurgic_infuser":2,"botania:red_mystical_flower":13,"mekanism:qio_drive_array":1,"forbidden_arcanus:arcane_polished_darkstone_pillar":1,"minecraft:ink_sac":6,"cyclic:sandstone_sword":1,"powah:thermoelectric_plate":1,"forbidden_arcanus:edelwood_log":4,"refinedstorage:wireless_transmitter":1,"craftandhunt:bear_brown_helmet":1,"minecraft:granite":19,"engineerstools:tracker":1,"forbidden_arcanus:cherrywood_sapling":24,"forbidden_arcanus:bone_shovel":1,"create:lime_valve_handle":1,"mekanism:advanced_energy_cube":1,"minecraft:bread":2,"thermal:coal_coke":1,"thermal:dynamo_lapidary":1,"iceandfire:dragon_skull_lightning":2,"minecraft:crafting_table":2,"forbidden_arcanus:cherrywood_log":64,"minecraft:clay_ball":64,"craftandhunt:golem_kit":1,"minecraft:leather_leggings":1,"backpacked:backpack":1,"ars_nouveau:volcanic_accumulator":1,"pamhc2crops:parsnipitem":19,"craftandhunt:calamari":8,"iceandfire:sea_serpent_scales_blue":15,"mysticalagriculture:tertium_ingot_block":1,"minecraft:cornflower":3,"refinedstorage:crafting_grid":1,"pneumaticcraft:programmable_controller":1,"engineerstools:material_box":1,"immersiveengineering:windmill":1,"minecraft:cracked_stone_bricks":3,"minecraft:cartography_table":1,"create:brass_funnel":1,"minecraft:poppy":2,"minecraft:spruce_slab":62,"quark:yellow_blossom_sapling":15,"minecraft:chest":10,"globalxp:xp_block":1,"byg:orange_oak_sapling":2,"minecraft:egg":8,"pamhc2crops:garlicitem":5,"minecraft:sandstone":8,"modularrouters:mod_filter":1,"minecraft:oak_door":11,"minecraft:spruce_fence":1,"pamhc2foodcore:pumpkinbreaditem":1,"simplefarming:onion_seeds":3,"mekanism:ultimate_enriching_factory":1,"minecraft:redstone":3,"simplefarming:eggplant_seeds":2,"minecraft:chicken_spawn_egg":1,"iceandfire:dragon_skull_ice":1,"mekanism:crusher":2,"minecraft:diamond_chestplate":1,"rftoolsutility:wire":1,"iceandfire:armor_amythest_chestplate":1,"simplefarming:strawberries":28,"mekanism:osmium_compressor":4,"minecraft:hay_block":18,"botania:blue_mystical_flower":10,"minecraft:gold_ingot":5,"pamhc2crops:lettuceitem":35,"pamhc2crops:artichokeitem":15,"craftandhunt:u_bear_panda_helmet":1,"iceandfire:dragonarmor_dragonsteel_fire_tail":1,"pamhc2trees:breadfruititem":1,"botania:green_mystical_flower":4,"mekanism:elite_control_circuit":1,"byg:jacaranda_sapling":2,"pneumaticcraft:spawner_agitator":1,"iceandfire:sea_serpent_fang":5,"pamhc2trees:papayaitem":1,"simplefarming:onion":2,"minecraft:lily_pad":15,"industrialforegoing:mob_crusher":1,"simplefarming:broccoli":2,"pamhc2crops:flaxitem":28,"simplefarming:broccoli_seeds":2,"pamhc2trees:soursopitem":1,"upgrade_aquatic:blue_pickerelweed":6,"pamhc2trees:plumitem":1,"iceandfire:dragonarmor_diamond_body":1,"minecraft:stone_bricks":5,"minecraft:apple":19,"scuba_gear:scuba_leggings":1,"minecraft:iron_ore":18,"pamhc2crops:blackberryitem":2,"minecraft:glass_bottle":1,"mysticalagriculture:jump_boost_iii_augment":1,"simplefarming:quinoa_seeds":3,"dankstorage:dank_1":2,"ars_nouveau:ab_smooth_slab":1,"mekanism:robit":3,"simplefarming:blueberries":34,"minecraft:gravel":4,"aquaculture:red_grouper":1,"minecraft:spruce_sapling":38,"mekanism:atomic_disassembler":1,"minecraft:spruce_log":130,"pneumaticcraft:assembly_platform":1,"simplefarming:cucumber":4,"variant16x:paeonia":2,"immersiveengineering:stairs_treated_wood_packaged":1,"pamhc2trees:peachitem":3,"simplefarming:raspberry_bush":9,"minecraft:leather_helmet":1,"appliedenergistics2:sky_stone_block":259,"appliedenergistics2:pink_smart_dense_cable":1,"aquaculture:atlantic_herring_bucket":1,"elementalcraft:whiterock_slab":1,"minecraft:slime_ball":1,"immersiveengineering:seed":13,"bloodmagic:soulgempetty":1,"astralsorcery:infused_wood_enriched":1,"minecraft:melon_seeds":1,"pamhc2foodcore:groundbeefitem":1,"ars_nouveau:mana_berry":1,"pamhc2crops:cornitem":20,"pamhc2crops:elderberryitem":26,"mekanism:electrolytic_separator":2,"simplefarming:turnip_seeds":1,"mekanismgenerators:turbine_casing":2,"bigreactors:reinforced_turbinerotorshaft":1,"minecraft:turtle_egg":1,"ars_nouveau:void_jar":1,"betterdefaultbiomes:white_mushroom":2,"appliedenergistics2:certus_quartz_wrench":1,"pamhc2trees:avocadoitem":1,"bloodmagic:ingot_hellforged":1,"craftingstation:crafting_station":1,"betterdefaultbiomes:swamp_willow_sapling":1,"elementalcraft:whiterock":7,"ringsofascension:ring_jump_boost":1,"tetra:metal_scrap":1,"elementalcraft:firecrystal":6,"minecraft:iron_pickaxe":1,"upgrade_aquatic:embedded_ammonite":1,"alexsmobs:raccoon_tail":1,"craftandhunt:lightning_rod":1,"silentgear:helmet_template":1,"iceandfire:dragonforge_ice_core":1,"silents_mechanisms:refinery":1,"ars_nouveau:glyph_smelt":1,"minecraft:stick":65,"botania:thunder_sword":1,"xreliquary:zombie_heart":2,"forbidden_arcanus:tentacle":2,"minecraft:oak_fence":1,"scuba_gear:scuba_helmet":2,"botania:yellow_mystical_flower":9,"minecraft:spruce_stairs":16,"thermal:diving_helmet":1,"minecraft:snow_block":1,"druidcraft:elderflower":1,"minecraft:diorite":192,"simplefarming:sweet_potato":2,"thermal:machine_furnace":1,"quark:spruce_vertical_slab":3,"mahoutsukai:murky_bucket":1,"elementalcraft:earth_shard":13,"botanypots:red_botany_pot":1,"byg:aspen_sapling":5,"byg:pine_sapling":12,"eidolon:tattered_cloth":10,"betterdefaultbiomes:purple_verbena":8,"pamhc2crops:chilipepperitem":31,"forbidden_arcanus:orb_of_temporary_flight":1,"minecraft:rotten_flesh":64,"astralsorcery:black_marble_pillar":1,"prettypipes:low_crafting_module":1,"xreliquary:ice_magus_rod":1,"glassential:glass_dark_ethereal":1,"minecraft:cobblestone":12,"minecraft:nautilus_shell":1,"upgrade_aquatic:purple_pickerelweed":41,"minecraft:leather_chestplate":1,"quantumstorage:quantum_bag_lime":1,"minecraft:andesite":62,"thermal:phytogro":1,"woodcutter:woodcutter":1,"iceandfire:armor_red_chestplate":1,"simplefarming:chicory_root":18,"minecraft:skull_banner_pattern":1,"druidcraft:elderberries":1,"minecraft:acacia_boat":9,"pamhc2foodcore:basiccheeseburgeritem":1,"create:pulse_repeater":1,"minecraft:lapis_lazuli":4,"minecraft:dirt":3344,"ars_nouveau:belt_of_unstable_gifts":1,"minecraft:name_tag":1,"mysticalagriculture:water_breathing_augment":1,"minecraft:leather_boots":2,"minecraft:bone":3,"botania:cyan_mystical_flower":11,"modularrouters:speed_upgrade":1,"minecraft:wheat_seeds":55,"botania:pink_mystical_flower":8,"botania:purple_mystical_flower":14,"dankstorage:dank_3":1,"minecraft:mossy_stone_bricks":5,"dimstorage:dimensional_tank":1,"minecraft:fletching_table":1,"mysticalagriculture:tilling_aoe_ii_augment":1,"minecraft:bamboo":6,"mekanism:osmium_ore":4,"minecraft:oak_planks":2,"botania:gray_mystical_flower":4,"xreliquary:magazines/neutral_magazine":1,"thermal:bell_pepper_seeds":1,"thermal:sapphire_dust":1,"minecraft:diorite_wall":1,"mekanism:teleportation_core":3,"iceandfire:dread_portal":1,"minecraft:sand":518,"byg:orange_daisy":2,"minecraft:jungle_planks":1,"elementalcraft:drenched_iron_nugget":2,"pamhc2foodcore:macncheeseitem":1,"minecraft:cyan_bed":1,"minecraft:lily_of_the_valley":1,"naturesaura:sky_axe":1,"minecraft:mossy_cobblestone":5,"woot:intern":1,"mekanism:digital_miner":1,"dankstorage:dank_4":3,"elementalcraft:air_shard":24,"minecraft:diamond":5,"minecraft:black_concrete":8,"minecraft:spruce_boat":10,"waystones:waystone":1,"pamhc2crops:strawberryitem":10,"pamhc2crops:bakedcassavaitem":1,"simplefarming:mead":1,"tetra:chthonic_extractor_used":1,"minecraft:spruce_sign":55,"iceandfire:tide_deepblue_helmet":1,"minecraft:oak_sapling":13,"byg:cika_sapling":1,"elementalcraft:water_shard":8,"rats:idol_of_ratlantis":1,"simplefarming:pea_seeds":1,"byg:soapstone":1,"iceandfire:fire_lily":1,"minecraft:brown_mushroom":1,"pamhc2crops:amaranthitem":25,"mekanismgenerators:fusion_reactor_logic_adapter":1,"minecraft:gold_block":19,"vanillatweaks:sugarblock":1,"psi:cad_battery_ultradense":3,"forbidden_arcanus:mortem_chestplate":1,"simplefarming:sorghum_seeds":1,"druidcraft:hemp_seeds":4,"extcaves:mushroom_lumishroom":3,"pneumaticcraft:air_conditioning_upgrade":1,"naturesaura:animal_spawner":1,"bigreactors:yellorium_dust":1,"botania:ender_eye_block":1,"darkutils:charm_sleep":1,"extlights:xmas_leaves_bulb_smooth_redblue":1,"silentgear:material_grader":1,"iceandfire:dragonbone":14,"simplefarming:cantaloupe_seeds":1,"dankstorage:dank_2":4,"pamhc2trees:pinenutitem":1,"aquaculture:perch":1,"minecraft:trident":1,"ringsofascension:ring_slow_falling":1,"pamhc2trees:orangeitem":1,"simplefarming:raw_calamari":9,"thermal:signalum_plate":1,"minecraft:dark_oak_planks":3,"pamhc2crops:cranberryitem":3,"thermal:peanut_seeds":4,"minecraft:arrow":2,"botania:lime_mystical_flower":10,"refinedstorage:16k_storage_disk":1,"minecraft:pumpkin_pie":3,"minecraft:jungle_stairs":1,"upgrade_aquatic:driftwood_log":17,"powah:uraninite_raw_poor":2,"pamhc2crops:bellpepperitem":18,"astralsorcery:attunement_altar":1,"minecraft:saddle":1,"iceandfire:armor_sapphire_boots":1,"thermal:machine_refinery":1,"minecraft:turtle_spawn_egg":1,"supplementaries:faucet":1,"byg:rocky_stone":10,"forbidden_arcanus:edelwood_oil":1,"upgradednetherite:feather_upgraded_netherite_horse_armor":1,"silentgear:flax_seeds":6,"industrialforegoing:range_addon4":1,"minecraft:salmon":1,"minecraft:leather":4,"mysticalagriculture:dye_seeds":1,"minecraft:cut_sandstone":1,"pamhc2crops:barleyitem":20,"forbidden_arcanus:dark_beacon":3,"pamhc2trees:lemonitem":1,"pamhc2crops:juteitem":1,"minecraft:gunpowder":20,"pamhc2trees:walnutitem":1,"immersiveengineering:treated_wood_horizontal":13,"iceandfire:forest_troll_leather_helmet":1,"botania:light_blue_mystical_flower":9,"botania:black_mystical_flower":12,"mekanism:enriched_refined_obsidian":1,"dankstorage:3_to_4":1,"mekanism:enrichment_chamber":4,"appliedenergistics2:light_blue_covered_dense_cable":1,"pamhc2trees:peppercornitem":1,"mysticalagriculture:imperium_watering_can":1,"dankstorage:dank_7":1,"minecraft:iron_ingot":5,"mysticalagradditions:supremium_coal":1,"botania:rannuncarpus_chibi":1,"ironjetpacks:platinum_jetpack":1,"upgradednetherite:fire_upgraded_netherite_leggings":1,"pamhc2trees:hazelnutitem":3,"minecraft:book":36,"pamhc2crops:onionitem":18,"minecraft:pillager_spawn_egg":1,"simplefarming:apple_sapling":1,"simplefarming:rice_seeds":1,"pamhc2crops:mustardseedsitem":17,"mysticalagriculture:tertium_shovel":1,"rats:rat_upgrade_breeder":1,"waystones:mossy_waystone":1,"minecraft:dandelion":1,"psi:cad_colorizer_green":1,"appliedenergistics2:yellow_covered_dense_cable":1,"minecraft:white_bed":1,"craftandhunt:guardian_elder_helmet":1,"mekanism:module_locomotive_boosting_unit":1,"simplefarming:blackberries":9,"create:extendo_grip":1,"simplefarming:sorghum_porridge":1,"minecraft:pumpkin_seeds":1,"simplefarming:strawberry_bush":6,"upgradednetherite:wither_upgraded_netherite_leggings":1,"byg:palo_verde_log":13,"pamhc2trees:guavaitem":1,"xreliquary:frozen_core":1,"iceandfire:tide_teal_leggings":1,"botania:azulejo_13":1,"minecraft:coal":3},"minecraft:used":{"minecraft:beetroot":1,"elementalcraft:whiterock_slab":1,"byg:aspen_sapling":3,"minecraft:spruce_slab":176,"minecraft:chest":8,"mekanism:digital_miner":1,"refinedstorage:wireless_transmitter":1,"minecraft:spruce_boat":9,"minecraft:lava_bucket":1,"variant16x:paeonia":1,"scannable:module_block":13,"minecraft:diorite_wall":31,"pamhc2trees:guavaitem":1,"simplefarming:onion":2,"simplefarming:sweet_potato":2,"minecraft:oak_sapling":10,"minecraft:cooked_cod":1,"minecraft:egg":4,"simplefarming:chicory_root":2,"minecraft:potato":1,"minecraft:diorite":20,"upgrade_aquatic:mulberry":1,"simplefarming:sorghum_bread":1,"pamhc2crops:elderberryitem":1,"pamhc2crops:lettuceitem":6,"mekanism:basic_infusing_factory":2,"minecraft:sand":10,"storagedrawers:acacia_full_drawers_1":4,"minecraft:black_concrete_powder":8,"mekanism:advanced_energy_cube":1,"byg:orange_oak_sapling":2,"byg:pine_sapling":10,"rats:cheese":1,"powah:thermo_generator_hardened":1,"globalxp:xp_block":1,"byg:jacaranda_sapling":1,"minecraft:poisonous_potato":1,"pamhc2crops:bakedcassavaitem":1,"minecraft:iron_bars":1,"forbidden_arcanus:dark_beacon":2,"simplefarming:sorghum_porridge":1,"minecraft:cooked_salmon":1,"byg:cika_sapling":1,"supplementaries:faucet":1,"druidcraft:lavender":4,"enigmaticlegacy:common_potion":1,"mekanism:osmium_compressor":2,"pamhc2crops:chilipepperitem":1,"aquaculture:red_grouper":1,"minecraft:bamboo":6,"constructionwand:diamond_wand":16,"forbidden_arcanus:cherrywood_sapling":1,"minecraft:water_bucket":1,"dankstorage:dank_7":2,"dankstorage:3_to_4":1,"byg:palo_verde_log":13,"byg:rocky_stone":1,"minecraft:fletching_table":1,"woodcutter:woodcutter":1,"pamhc2trees:plumitem":1,"minecraft:cracked_stone_bricks":2,"minecraft:salmon":1,"pamhc2foodcore:basiccheeseburgeritem":1,"minecraft:mossy_cobblestone":2,"minecraft:crafting_table":2,"pamhc2trees:soursopitem":1,"minecraft:spruce_log":71,"pamhc2trees:orangeitem":1,"mekanism:atomic_disassembler":2271,"minecraft:suspicious_stew":1,"refinedstorage:crafting_grid":1,"minecraft:spruce_sapling":2,"minecraft:cobblestone":10,"ars_nouveau:mana_berry":2,"forbidden_arcanus:cherry_peach":2,"pamhc2trees:breadfruititem":1,"simplefarming:cumin_seeds":1,"mekanism:nutritional_liquifier":1,"simplefarming:blueberries":3,"mekanism:basic_universal_cable":4,"byg:palo_verde_sapling":2,"refinedstorage:controller":1,"simplefarming:corn":1,"pamhc2crops:peanutitem":9,"minecraft:stone_bricks":3,"thermal:peanut_seeds":1,"minecraft:brown_carpet":2,"minecraft:gold_block":9,"refinedstorage:disk_drive":1,"pamhc2trees:walnutitem":1,"pamhc2trees:cherryitem":1,"minecraft:oak_planks":1,"pamhc2trees:bananaitem":1,"pamhc2trees:peachitem":1,"simplefarming:strawberries":5,"pamhc2foodcore:pumpkinbreaditem":1,"waystones:waystone":1,"mekanism:crusher":2,"minecraft:bread":12,"mekanism:metallurgic_infuser":2,"elementalcraft:whiterock":4,"minecraft:gravel":3,"pamhc2foodcore:macncheeseitem":1,"pamhc2trees:pinenutitem":1,"minecraft:andesite":12,"mekanismtools:steel_paxel":1318,"aquaculture:perch":1,"minecraft:oak_fence":1,"storagedrawers:oak_full_drawers_1":1,"minecraft:trident":2,"mekanism:enrichment_chamber":3,"minecraft:rose_bush":1,"pamhc2crops:cranberryitem":1,"minecraft:spruce_planks":5,"simplefarming:sunflower_seeds":3,"dimstorage:dimensional_tank":3,"minecraft:dirt":146,"minecraft:spruce_stairs":22,"pamhc2crops:garlicitem":2,"minecraft:spruce_fence":2,"minecraft:granite":5,"pamhc2trees:avocadoitem":1,"extcaves:mushroom_lumishroom":1,"minecraft:dark_oak_planks":2,"simplefarming:pasta":21,"pamhc2crops:onionitem":1,"quark:spruce_vertical_slab":12,"engineerstools:musli_bar":21,"simplefarming:broccoli":1,"minecraft:acacia_boat":8,"dankstorage:dock":1,"minecraft:brown_mushroom":1,"minecraft:spruce_sign":2,"minecraft:green_bed":2,"simplefarming:blackberries":1,"pamhc2trees:hazelnutitem":3,"pamhc2trees:papayaitem":1,"simplefarming:cucumber":1,"minecraft:flower_pot":3,"minecraft:apple":6,"mekanism:ultimate_enriching_factory":1,"craftingstation:crafting_station":2,"waystones:mossy_waystone":1,"betterdefaultbiomes:purple_verbena":3,"pamhc2foodcore:groundbeefitem":1,"minecraft:jungle_stairs":1,"byg:orange_daisy":2,"thermal:bell_pepper_seeds":1,"minecraft:bucket":1,"minecraft:pumpkin_pie":20,"pamhc2crops:cucumberitem":1},"minecraft:crafted":{"minecraft:black_dye":1,"minecraft:beacon":1,"mekanism:energy_tablet":1,"craftingstation:crafting_station":1,"minecraft:spruce_fence":3,"scuba_gear:scuba_helmet":1,"minecraft:spruce_stairs":8,"minecraft:black_concrete_powder":8,"minecraft:spruce_slab":156,"minecraft:spruce_boat":2,"dankstorage:dank_1":1,"mekanismtools:steel_paxel":4,"dankstorage:dank_3":1,"minecraft:oak_planks":16,"mekanism:atomic_disassembler":1,"minecraft:chest":4,"iceandfire:dragonscales_sapphire":9,"minecraft:crafting_table":2,"minecraft:spruce_planks":124,"lootbagmod:lootbag":1,"minecraft:gold_block":3,"minecraft:string":1,"mekanism:steel_casing":1,"minecraft:iron_ingot":27,"quark:spruce_vertical_slab":9,"minecraft:spruce_log":48,"minecraft:sugar":9,"minecraft:spruce_sign":3,"minecraft:diorite_wall":30,"minecraft:acacia_boat":1,"dankstorage:dock":1,"mysticalagriculture:tertium_ingot":9,"minecraft:acacia_planks":8},"minecraft:dropped":{"mekanism:electrolytic_separator":2,"minecraft:glass_bottle":1,"extcaves:mushroom_lumishroom":1,"thermal:peanut_seeds":3,"dankstorage:dock":1,"dankstorage:dank_3":2,"dankstorage:dank_1":1,"minecraft:wheat_seeds":5,"upgrade_aquatic:flowering_rush":1,"minecraft:spruce_fence":1,"minecraft:spruce_boat":2,"simplefarming:cucumber_seeds":2,"minecraft:spruce_sign":55,"mekanism:atomic_disassembler":1,"pamhc2crops:juteitem":1,"psi:cad_battery_ultradense":3,"minecraft:pumpkin_pie":3,"mcwtrpdoors:print_four_panel":2,"pamhc2crops:garlicitem":2,"immersiveengineering:seed":1,"dankstorage:dank_2":4,"minecraft:stick":13,"simplefarming:broccoli_seeds":2,"simplefarming:onion_seeds":3,"mekanism:osmium_compressor":2,"mekanism:alloy_reinforced":2,"dankstorage:dank_4":2}},"DataVersion":2586}